setup.py
mcserver_wrapper.egg-info/PKG-INFO
mcserver_wrapper.egg-info/SOURCES.txt
mcserver_wrapper.egg-info/dependency_links.txt
mcserver_wrapper.egg-info/entry_points.txt
mcserver_wrapper.egg-info/top_level.txt
mcwrapper/__init__.py
mcwrapper/alarm.py
mcwrapper/mod.py
mcwrapper/players.py
mcwrapper/prints.py
mcwrapper/status.py
mcwrapper/wrapper.py