Metadata-Version: 1.1
Name: mcserver-wrapper
Version: 0.5
Summary: Minecraft server wrapper
Home-page: https://github.com/Cynerd/mcserver-wrapper
Author: Cynerd
Author-email: cynerd@email.cz
License: GPLv2
Keywords: Minecraft wrapper server
Platform: UNKNOWN
Classifier: Development Status :: 3 - Alpha
Classifier: Programming Language :: Python :: 3
Classifier: Programming Language :: Python :: 3.3
Classifier: Programming Language :: Python :: 3.4
Classifier: Programming Language :: Python :: 3.5
Classifier: Programming Language :: Python :: 3.6
